{
    "affycoretools": [
        "ReportingTools",
        "biovizBase",
        "ggbio"
    ],
    "AgiMicroRna": [
        "ReportingTools",
        "affycoretools",
        "biovizBase",
        "ggbio"
    ],
    "AllelicImbalance": [
        "Gviz",
        "biovizBase"
    ],
    "alpine": [],
    "amplican": [],
    "AneuFinder": [],
    "APAlyzer": [],
    "appreci8R": [],
    "ArrayExpressHTS": [],
    "arrayMvout": [
        "lumi"
    ],
    "ASpediaFI": [
        "Gviz",
        "biovizBase"
    ],
    "ASpli": [
        "Gviz",
        "biovizBase"
    ],
    "ATACCoGAPS": [
        "chromVAR",
        "motifmatchr",
        "projectR"
    ],
    "ATACseqQC": [
        "ChIPpeakAnno",
        "motifStack"
    ],
    "ATACseqTFEA": [
        "motifmatchr"
    ],
    "atSNP": [
        "motifStack"
    ],
    "BadRegionFinder": [],
    "BANDITS": [
        "DRIMSeq"
    ],
    "banocc": [],
    "BASiCStan": [],
    "BBCAnalyzer": [],
    "benchdamic": [],
    "bigmelon": [
        "lumi",
        "wateRmelon"
    ],
    "BindingSiteFinder": [
        "Gviz",
        "biovizBase"
    ],
    "biomvRCNS": [
        "Gviz",
        "biovizBase"
    ],
    "biovizBase": [],
    "biscuiteer": [
        "dmrseq"
    ],
    "BitSeq": [],
    "BOBaFIT": [
        "biovizBase",
        "ggbio"
    ],
    "borealis": [],
    "brainflowprobes": [
        "GenomicFiles",
        "biovizBase",
        "derfinder",
        "derfinderPlot",
        "ggbio"
    ],
    "BubbleTree": [
        "biovizBase"
    ],
    "CAFE": [
        "biovizBase",
        "ggbio"
    ],
    "CAGEfightR": [
        "GenomicFiles",
        "GenomicInteractions",
        "Gviz",
        "biovizBase"
    ],
    "cageminer": [
        "biovizBase",
        "ggbio"
    ],
    "cardelino": [],
    "cbaf": [
        "cBioPortalData"
    ],
    "cBioPortalData": [],
    "ChAMP": [
        "DMRcate",
        "Gviz",
        "biovizBase",
        "lumi",
        "missMethyl",
        "wateRmelon"
    ],
    "ChIC": [],
    "chimeraviz": [
        "Gviz",
        "biovizBase"
    ],
    "ChIPexoQual": [
        "biovizBase"
    ],
    "ChIPpeakAnno": [],
    "ChIPQC": [],
    "chromVAR": [],
    "cicero": [
        "Gviz",
        "biovizBase"
    ],
    "circRNAprofiler": [
        "gwascat"
    ],
    "CircSeqAlignTk": [],
    "CiteFuse": [],
    "CNVfilteR": [
        "CopyNumberPlots",
        "biovizBase",
        "karyoploteR"
    ],
    "CNViz": [
        "CopyNumberPlots",
        "biovizBase",
        "karyoploteR"
    ],
    "COCOA": [],
    "comapr": [
        "Gviz",
        "biovizBase"
    ],
    "coMET": [
        "Gviz",
        "biovizBase"
    ],
    "compartmap": [],
    "compEpiTools": [
        "Gviz",
        "biovizBase",
        "methylPipe"
    ],
    "consensusDE": [],
    "contiBAIT": [
        "GenomicFiles"
    ],
    "CopyNumberPlots": [
        "biovizBase",
        "karyoploteR"
    ],
    "CoreGx": [],
    "crisprDesign": [],
    "crisprseekplus": [
        "ChIPpeakAnno",
        "GUIDEseq"
    ],
    "crisprVerse": [
        "Gviz",
        "biovizBase",
        "crisprDesign",
        "crisprViz"
    ],
    "crisprViz": [
        "Gviz",
        "biovizBase",
        "crisprDesign"
    ],
    "cummeRbund": [
        "Gviz",
        "biovizBase"
    ],
    "customProDB": [],
    "CyTOFpower": [
        "CytoGLMM"
    ],
    "CytoGLMM": [],
    "dagLogo": [
        "motifStack"
    ],
    "decompTumor2Sig": [],
    "deepSNV": [],
    "DeMixT": [],
    "derfinder": [
        "GenomicFiles"
    ],
    "derfinderPlot": [
        "GenomicFiles",
        "biovizBase",
        "derfinder",
        "ggbio"
    ],
    "DEScan2": [
        "ChIPpeakAnno"
    ],
    "DifferentialRegulation": [
        "BANDITS",
        "DRIMSeq"
    ],
    "DMCFB": [],
    "DMRcate": [
        "Gviz",
        "biovizBase",
        "missMethyl"
    ],
    "DMRforPairs": [
        "Gviz",
        "biovizBase"
    ],
    "dmrseq": [],
    "DominoEffect": [],
    "DRIMSeq": [],
    "ELMER": [
        "Gviz",
        "biovizBase"
    ],
    "enhancerHomologSearch": [
        "motifmatchr"
    ],
    "enrichTF": [
        "motifmatchr"
    ],
    "ensemblVEP": [],
    "epialleleR": [],
    "epihet": [],
    "epimutacions": [
        "Gviz",
        "biovizBase"
    ],
    "EpiTxDb": [],
    "epivizr": [],
    "epivizrChart": [],
    "epivizrStandalone": [
        "epivizr"
    ],
    "erma": [
        "GenomicFiles"
    ],
    "esATAC": [
        "motifmatchr"
    ],
    "EventPointer": [],
    "exomePeak2": [],
    "ExperimentHubData": [],
    "extraChIPs": [
        "GenomicInteractions",
        "Gviz",
        "biovizBase"
    ],
    "ffpe": [
        "lumi"
    ],
    "FLAMES": [
        "biovizBase",
        "ggbio"
    ],
    "flowCL": [],
    "GA4GHshiny": [],
    "genbankr": [],
    "geneRxCluster": [],
    "GeneStructureTools": [
        "Gviz",
        "biovizBase"
    ],
    "GenomicFiles": [],
    "GenomicInteractions": [
        "Gviz",
        "biovizBase"
    ],
    "GenomicOZone": [
        "biovizBase",
        "ggbio"
    ],
    "GenVisR": [],
    "ggbio": [
        "biovizBase"
    ],
    "gmapR": [],
    "gscreend": [],
    "GUIDEseq": [
        "ChIPpeakAnno"
    ],
    "Gviz": [
        "biovizBase"
    ],
    "gwascat": [],
    "HelloRanges": [],
    "HiCDCPlus": [
        "GenomicInteractions",
        "Gviz",
        "biovizBase"
    ],
    "HiContacts": [
        "GenomicInteractions",
        "Gviz",
        "biovizBase"
    ],
    "HTSeqGenie": [
        "VariantTools",
        "gmapR"
    ],
    "icetea": [],
    "iCheck": [
        "lumi"
    ],
    "IgGeneUsage": [],
    "igvR": [],
    "imcRtools": [],
    "intansv": [
        "biovizBase",
        "ggbio"
    ],
    "IPO": [],
    "ISAnalytics": [],
    "IsoformSwitchAnalyzeR": [
        "DRIMSeq"
    ],
    "karyoploteR": [
        "biovizBase"
    ],
    "katdetectr": [],
    "kissDE": [],
    "lineagespot": [],
    "lisaClust": [],
    "LowMACA": [
        "cBioPortalData",
        "motifStack"
    ],
    "lumi": [],
    "M3Drop": [],
    "MADSEQ": [],
    "MAGAR": [
        "RnBeads"
    ],
    "maser": [
        "Gviz",
        "biovizBase"
    ],
    "MatrixRider": [],
    "mCSEA": [
        "Gviz",
        "biovizBase"
    ],
    "MEAL": [
        "Gviz",
        "biovizBase",
        "missMethyl"
    ],
    "MEAT": [
        "lumi",
        "wateRmelon"
    ],
    "MetaboSignal": [
        "MWASTools"
    ],
    "metaseqR2": [],
    "metavizr": [
        "epivizr",
        "epivizrStandalone"
    ],
    "MethCP": [],
    "methylclock": [
        "ExperimentHubData"
    ],
    "methylGSA": [
        "missMethyl"
    ],
    "methylPipe": [
        "Gviz",
        "biovizBase"
    ],
    "methylSig": [],
    "microbiomeMarker": [],
    "MineICA": [
        "lumi"
    ],
    "MinimumDistance": [],
    "missMethyl": [],
    "mitoClone2": [
        "deepSNV"
    ],
    "MMAPPR2": [
        "VariantTools",
        "ensemblVEP",
        "gmapR"
    ],
    "monaLisa": [],
    "motifbreakR": [
        "Gviz",
        "biovizBase",
        "motifStack"
    ],
    "motifmatchr": [],
    "motifStack": [],
    "msgbsR": [
        "biovizBase",
        "ggbio"
    ],
    "multicrispr": [
        "biovizBase",
        "karyoploteR"
    ],
    "multiSight": [],
    "MungeSumstats": [],
    "musicatk": [
        "decompTumor2Sig"
    ],
    "MutationalPatterns": [],
    "MWASTools": [],
    "myvariant": [],
    "NADfinder": [
        "ATACseqQC",
        "ChIPpeakAnno",
        "Gviz",
        "biovizBase",
        "motifStack",
        "trackViewer"
    ],
    "NBSplice": [],
    "netZooR": [
        "yarn"
    ],
    "nullranges": [],
    "octad": [],
    "ODER": [
        "GenomicFiles",
        "derfinder"
    ],
    "OGRE": [
        "Gviz",
        "biovizBase"
    ],
    "omada": [],
    "OMICsPCA": [
        "HelloRanges"
    ],
    "pageRank": [
        "motifmatchr"
    ],
    "panelcn.mops": [],
    "PDATK": [
        "CoreGx"
    ],
    "PharmacoGx": [
        "CoreGx"
    ],
    "PING": [
        "Gviz",
        "biovizBase"
    ],
    "ppcseq": [],
    "primirTSS": [
        "Gviz",
        "biovizBase"
    ],
    "PrInCE": [],
    "projectR": [],
    "ProteoDisco": [],
    "psichomics": [
        "GenomicFiles",
        "derfinder",
        "recount"
    ],
    "PureCN": [],
    "Pviz": [
        "Gviz",
        "biovizBase"
    ],
    "qrqc": [
        "biovizBase"
    ],
    "QuasR": [
        "GenomicFiles"
    ],
    "R3CPET": [
        "biovizBase",
        "ggbio"
    ],
    "R453Plus1Toolbox": [],
    "RadioGx": [
        "CoreGx"
    ],
    "RareVariantVis": [],
    "recount": [
        "GenomicFiles",
        "derfinder"
    ],
    "REDseq": [
        "ChIPpeakAnno"
    ],
    "regioneReloaded": [],
    "regionReport": [
        "GenomicFiles",
        "derfinder"
    ],
    "regutools": [
        "Gviz",
        "biovizBase"
    ],
    "ReportingTools": [
        "biovizBase",
        "ggbio"
    ],
    "RgnTX": [],
    "RiboCrypt": [],
    "RiboDiPA": [],
    "RiboProfiling": [
        "biovizBase",
        "ggbio"
    ],
    "ribosomeProfilingQC": [
        "motifStack"
    ],
    "RIPAT": [
        "biovizBase",
        "karyoploteR"
    ],
    "RLSeq": [],
    "RNAAgeCalc": [
        "GenomicFiles",
        "derfinder",
        "recount"
    ],
    "RNAmodR": [
        "Gviz",
        "biovizBase"
    ],
    "RNAmodR.AlkAnilineSeq": [
        "Gviz",
        "RNAmodR",
        "biovizBase"
    ],
    "RNAmodR.ML": [
        "Gviz",
        "RNAmodR",
        "biovizBase"
    ],
    "RNAmodR.RiboMethSeq": [
        "Gviz",
        "RNAmodR",
        "biovizBase"
    ],
    "RnaSeqSampleSize": [
        "GenomicFiles",
        "derfinder",
        "recount"
    ],
    "RnBeads": [],
    "Rqc": [
        "GenomicFiles",
        "biovizBase"
    ],
    "sccomp": [],
    "scMerge": [
        "M3Drop"
    ],
    "scMET": [],
    "scmeth": [],
    "scone": [],
    "scoreInvHap": [],
    "scruff": [
        "biovizBase",
        "ggbio"
    ],
    "scTreeViz": [
        "epivizr"
    ],
    "selectKSigs": [],
    "seqCAT": [],
    "signeR": [],
    "SigsPack": [],
    "simpleSeg": [],
    "singleCellTK": [
        "M3Drop",
        "scMerge"
    ],
    "SingleMoleculeFootprinting": [
        "GenomicFiles",
        "QuasR"
    ],
    "skewr": [
        "lumi",
        "wateRmelon"
    ],
    "SNPhood": [],
    "sojourner": [],
    "SomaticSignatures": [
        "biovizBase",
        "ggbio"
    ],
    "SparseSignatures": [],
    "spatzie": [
        "GenomicInteractions",
        "Gviz",
        "biovizBase",
        "motifmatchr"
    ],
    "SPLINTER": [
        "Gviz",
        "biovizBase"
    ],
    "srnadiff": [
        "Gviz",
        "biovizBase"
    ],
    "stageR": [],
    "STAN": [
        "Gviz",
        "biovizBase"
    ],
    "standR": [],
    "StructuralVariantAnnotation": [],
    "svaNUMT": [
        "StructuralVariantAnnotation"
    ],
    "svaRetro": [
        "StructuralVariantAnnotation"
    ],
    "TCGAbiolinksGUI": [
        "ELMER",
        "Gviz",
        "biovizBase"
    ],
    "TDARACNE": [],
    "TFHAZ": [],
    "timeOmics": [],
    "TitanCNA": [],
    "tLOH": [],
    "ToxicoGx": [
        "CoreGx"
    ],
    "trackViewer": [
        "Gviz",
        "biovizBase"
    ],
    "TraRe": [],
    "traseR": [],
    "tscR": [],
    "TVTB": [
        "Gviz",
        "biovizBase",
        "ensemblVEP"
    ],
    "UMI4Cats": [],
    "uncoverappLib": [
        "Gviz",
        "biovizBase"
    ],
    "Uniquorn": [],
    "VariantFiltering": [
        "Gviz",
        "biovizBase"
    ],
    "VariantTools": [],
    "VCFArray": [
        "GenomicFiles"
    ],
    "Voyager": [],
    "vtpnet": [
        "gwascat"
    ],
    "vulcan": [
        "ChIPpeakAnno"
    ],
    "wateRmelon": [
        "lumi"
    ],
    "Xeva": [
        "CoreGx",
        "PharmacoGx"
    ],
    "YAPSA": [
        "SomaticSignatures",
        "biovizBase",
        "ggbio"
    ],
    "yarn": []
}